projeto/unidade_de_controle.vhd
-- library declaration
library IEEE;
use IEEE.std_logic_1164.all;

-- entity
entity unidade_de_controle is 
    port(
        inicia_b, para_b, reset_b : in std_logic;
        clock: in  std_logic;
        ativado, reset : out std_logic
    );
end unidade_de_controle;

-- architecture
architecture arch of unidade_de_controle is
    type state_type is (zera, parado, contando);
    signal CurrentState, NextState : state_type;
begin  
    update_state: process (clock, reset_b) --talvez dê errado
    begin
        if (reset_b = '0') then
            CurrentState <= zera;
        elsif (rising_edge(clock)) then 
            CurrentState <= NextState;
        end if;
    end process update_state;
    
    update_output: process (CurrentState)
    begin
        case CurrentState is 
            when zera =>
                ativado <= '0';
                reset <= '1';
            when parado =>
                ativado <= '0';
                reset <= '0';
            when contando => 
                ativado <= '1';
                reset <= '0';
            end case;
        end process update_output;

    update_next_state: process(inicia_b, para_b, reset_b)
    begin
        case CurrentState is 
            when zera =>
                NextState <= parado;
            when parado =>
                if inicia_b = '0' then
                    NextState <= contando;
                else 
                    NextState <= parado;
                end if;
            when contando => 
                if para_b = '0' then
                    NextState <= parado;
                else
                    NextState <= contando;
                end if;
        end case;
    end process update_next_state;
end arch;

projeto/codificador_hexadecimal.vhd
library IEEE;
use IEEE.STD_LOGIC_1164.ALL;
use ieee.numeric_std.all;

ENTITY codificador_hexadecimal IS 
    PORT(
        entrada_bin : in std_logic_vector(3 downto 0);
        saida_hexa : out std_logic_vector(6 downto 0)
    );
END codificador_hexadecimal;

ARCHITECTURE codificador_hexadecimal_arch of codificador_hexadecimal is

begin

    PROCESS (entrada_bin)
    begin
        CASE entrada_bin is
            WHEN "0000" =>
                saida_hexa <= "0000001";
            WHEN "0001" =>
                saida_hexa <= "1001111";
            WHEN "0010" =>
                saida_hexa <= "0010010";
            WHEN "0011" =>
                saida_hexa <= "0000110";
            WHEN "0100" =>
                saida_hexa <= "1001100";
            WHEN "0101" =>
                saida_hexa <= "0100100";
            WHEN "0110" =>
                saida_hexa <= "0100000";
            WHEN "0111" =>
                saida_hexa <= "0001111";
            WHEN "1000" =>
                saida_hexa <= "0000000";
            WHEN "1001" =>
                saida_hexa <= "0001100";
            WHEN "1010" =>
                saida_hexa <= "0001000";
            WHEN "1011" =>
                saida_hexa <= "1100000";
            WHEN "1100" =>
                saida_hexa <= "0110001";
            WHEN "1101" =>
                saida_hexa <= "1000010";
            WHEN "1110" =>
                saida_hexa <= "0110000";
            WHEN "1111" =>
                saida_hexa <= "0111000";
            WHEN others =>
                saida_hexa <= "1111111";
        END CASE; 
    END PROCESS;

END ARCHITECTURE;

projeto/flipflop.vhd
library IEEE;
use IEEE.STD_LOGIC_1164.ALL;

entity flipflop IS 
    port(
        D : in std_logic;
        clock : in std_logic;
        reset : in std_logic;
        preset: in std_logic;
        Q : out std_logic
    );
end flipflop;

architecture flipflop_arch of flipflop is

signal Q_s : std_logic := '0';

begin

    process(clock, D, reset, preset)
    begin
        if reset = '1' then
            Q_s <= '0';
        elsif preset = '1' then
            Q_s <= '1';
        elsif rising_edge(clock) then
            Q_s <= D;
        end if;
    end process;

    Q <= Q_s;

end architecture;

projeto/contador.vhd
library IEEE;
use IEEE.STD_LOGIC_1164.ALL;
use ieee.numeric_std.all;

entity contador IS 
    generic(
        max : integer := 15
    );
    port(
        clock : in std_logic;
        Q : out std_logic_vector(3 downto 0);
        full : out std_logic;
        reset : in std_logic
    );
end contador;

architecture contador_arch of contador is

component flipflop IS 
    port(
        D : in std_logic;
        clock : in std_logic;
        reset : in std_logic;
        preset: in std_logic;
        Q : out std_logic
    );
end component;

signal Q_integer_s :  integer range 0 to 15 := 0;
signal full_s, full_del_1_s, full_out_s : std_logic := '0';
signal n_clock_s : std_logic;
signal Q_s : std_logic_vector(3 downto 0) := "0000";

begin

    n_clock_s <= NOT(clock);


    process(clock, reset, Q_integer_s)
    begin
        if reset = '1' then
            Q_integer_s <= 0;
        elsif rising_edge(clock) then
            if Q_integer_s = max then 
                Q_integer_s <= 0;
                -- full <= '1';
            elsif Q_integer_s < max then
                Q_integer_s <= Q_integer_s + 1;
                -- full <= '0';
            end if;
        end if;
    end process;

    full_s <= '1' when Q_integer_s = max else '0';

    Q_s <= std_logic_vector(to_unsigned(Q_integer_s, Q_s'length));
    Q <= Q_s;

    delay_reg_1:flipflop 
        port map(
            D => full_s ,
            Q => full_del_1_s,
            reset => reset,
            preset => '0',
            clock => n_clock_s
    );

    delay_reg_2:flipflop 
        port map(
            D => full_del_1_s,
            Q => full_out_s ,
            reset => reset,
            preset => '0',
            clock => clock
    );

    full <= full_out_s;

end architecture;

projeto/fluxo_de_dados.vhd
library IEEE;
use IEEE.STD_LOGIC_1164.ALL;
use ieee.numeric_std.all;

entity fluxo_de_dados IS 
    port(
        clock : in std_logic;
        reset : in std_logic;
        ativado : in std_logic;

        Q0 : out std_logic_vector(3 downto 0);
        Q1 : out std_logic_vector(3 downto 0);
        Q2 : out std_logic_vector(3 downto 0);
        Q3 : out std_logic_vector(3 downto 0);
        Q4 : out std_logic_vector(3 downto 0);
        Q5 : out std_logic_vector(3 downto 0);

        display_0 : out std_logic_vector(6 downto 0);
        display_1 : out std_logic_vector(6 downto 0);
        display_2 : out std_logic_vector(6 downto 0);
        display_3 : out std_logic_vector(6 downto 0);
        display_4 : out std_logic_vector(6 downto 0);
        display_5 : out std_logic_vector(6 downto 0)

    );
end fluxo_de_dados;

architecture fluxo_de_dados_arch of fluxo_de_dados is

component contador IS 
    generic(
        max : integer := 15
    );
    port(
        clock : in std_logic;
        Q : out std_logic_vector(3 downto 0);
        full : out std_logic;
        reset : in std_logic
    );
end component;

component codificador_hexadecimal IS 
    PORT(
        entrada_bin : in std_logic_vector(3 downto 0);
        saida_hexa : out std_logic_vector(6 downto 0)
    );
END component;


signal Q0_s, Q1_s, Q2_s, Q3_s, Q4_s, Q5_s : std_logic_vector(3 downto 0);
signal full0_s, full1_s, full2_s, full3_s, full4_s, full5_s : std_logic;

signal clock_cont_0_s : std_logic;

begin

    clock_cont_0_s <= clock AND ativado;

    cont_0 : contador
        generic map(
            max => 9
        )
        port map(
            clock => clock_cont_0_s,
            Q => Q0_s,
            full => full0_s,
            reset => reset
        );
    cod_0 : codificador_hexadecimal port map(
        entrada_bin => Q0_s,
        saida_hexa => display_0
    );

    cont_1 : contador
        generic map(
            max => 9
        )
        port map(
            clock => full0_s,
            Q => Q1_s,
            full => full1_s,
            reset => reset
        );
    cod_1 : codificador_hexadecimal port map(
        entrada_bin => Q1_s,
        saida_hexa => display_1
    );

    cont_2 : contador
        generic map(
            max => 9
        )
        port map(
            clock => full1_s,
            Q => Q2_s,
            full => full2_s,
            reset => reset
        );
    cod_2 : codificador_hexadecimal port map(
        entrada_bin => Q2_s,
        saida_hexa => display_2
    );

    cont_3 : contador
        generic map(
            max => 5
        )
        port map(
            clock => full2_s,
            Q => Q3_s,
            full => full3_s,
            reset => reset
        );
    cod_3 : codificador_hexadecimal port map(
        entrada_bin => Q3_s,
        saida_hexa => display_3
    );

    cont_4 : contador
        generic map(
            max => 9
        )
        port map(
            clock => full3_s,
            Q => Q4_s,
            full => full4_s,
            reset => reset
        );
    cod_4 : codificador_hexadecimal port map(
        entrada_bin => Q4_s,
        saida_hexa => display_4
    );

    cont_5 : contador
        generic map(
            max => 5
        )
        port map(
            clock => full4_s,
            Q => Q5_s,
            full => full5_s,
            reset => reset
        );
    cod_5 : codificador_hexadecimal port map(
        entrada_bin => Q5_s,
        saida_hexa => display_5
    );


    Q0 <= Q0_s;
    Q1 <= Q1_s;
    Q2 <= Q2_s;
    Q3 <= Q3_s;
    Q4 <= Q4_s;
    Q5 <= Q5_s;


end architecture;

projeto/cronometro.vhd
library IEEE;
use IEEE.STD_LOGIC_1164.ALL;
use ieee.numeric_std.all;

ENTITY cronometro IS 
    PORT(
        inicia_b, para_b, reset_b : std_logic;
        clock: in  std_logic;

        display_0 : out std_logic_vector(6 downto 0);
        display_1 : out std_logic_vector(6 downto 0);
        display_2 : out std_logic_vector(6 downto 0);
        display_3 : out std_logic_vector(6 downto 0);
        display_4 : out std_logic_vector(6 downto 0);
        display_5 : out std_logic_vector(6 downto 0)
    );
END cronometro;

architecture cronometro_arch of cronometro is

component fluxo_de_dados IS 
    port(
        clock : in std_logic;
        reset : in std_logic;
        ativado : in std_logic;

        Q0 : out std_logic_vector(3 downto 0);
        Q1 : out std_logic_vector(3 downto 0);
        Q2 : out std_logic_vector(3 downto 0);
        Q3 : out std_logic_vector(3 downto 0);
        Q4 : out std_logic_vector(3 downto 0);
        Q5 : out std_logic_vector(3 downto 0);

        display_0 : out std_logic_vector(6 downto 0);
        display_1 : out std_logic_vector(6 downto 0);
        display_2 : out std_logic_vector(6 downto 0);
        display_3 : out std_logic_vector(6 downto 0);
        display_4 : out std_logic_vector(6 downto 0);
        display_5 : out std_logic_vector(6 downto 0)

    );
end component; 

component unidade_de_controle is 
    port(
        inicia_b, para_b, reset_b :in std_logic;
        clock: in  std_logic;
        ativado, reset : out std_logic
    );
end component;

signal Q0_s : std_logic_vector(3 downto 0);
signal Q1_s : std_logic_vector(3 downto 0);
signal Q2_s : std_logic_vector(3 downto 0);
signal Q3_s : std_logic_vector(3 downto 0);
signal Q4_s : std_logic_vector(3 downto 0);
signal Q5_s : std_logic_vector(3 downto 0);

signal ativado_s : std_logic;
signal reset_s : std_logic;

begin

    FD: fluxo_de_dados
    port map(
        clock => clock,
        reset => reset_s,
        ativado => ativado_s,

        Q0 => Q0_s,
        Q1 => Q1_s,
        Q2 => Q2_s,
        Q3 => Q3_s,
        Q4 => Q4_s,
        Q5 => Q5_s,

        display_0 => display_0,
        display_1 => display_1,
        display_2 => display_2,
        display_3 => display_3,
        display_4 => display_4,
        display_5 => display_5
    );

    UC : unidade_de_controle
    port map(
        inicia_b => inicia_b,
        para_b => para_b,
        reset_b => reset_b,
        clock => clock,
        ativado => ativado_s, 
        reset => reset_s
    );


end architecture;

projeto/tb_cronometro.vhd
library ieee;
use IEEE.STD_LOGIC_1164.ALL;
use ieee.math_real.ceil;
use ieee.math_real.log2;
use ieee.numeric_std.all;
entity tb_cronometro is
end tb_cronometro;

architecture tb_cronometro_arch of tb_cronometro is


component cronometro is
    port(
        inicia_b, para_b, reset_b : std_logic;
        clock: in  std_logic;

        display_0 : out std_logic_vector(6 downto 0);
        display_1 : out std_logic_vector(6 downto 0);
        display_2 : out std_logic_vector(6 downto 0);
        display_3 : out std_logic_vector(6 downto 0);
        display_4 : out std_logic_vector(6 downto 0);
        display_5 : out std_logic_vector(6 downto 0)
    );
end component;

	

	signal clock_in: std_logic := '0';
	signal reset_in: std_logic := '0';
	constant clockPeriod: time := 10 us; -- periodo do clock
	signal clock_enable : std_logic := '0';

    signal inicia_b_s, para_b_s, reset_b_s : std_logic := '1';

begin
	DUT: cronometro port map(
        inicia_b => inicia_b_s,
        para_b => para_b_s,
        reset_b => reset_b_s,
        clock => clock_in
    );
	
    clock_in <= (clock_enable and (not clock_in)) after clockPeriod/2;
	
	estimulos: process is
	begin
        clock_enable <= '1';
        wait for 20*clockPeriod;

        inicia_b_s <= '0';
        wait for 5*clockPeriod;
        inicia_b_s <= '1';

        wait for 10*clockPeriod;

        para_b_s <= '0';
        wait for 5*clockPeriod;
        para_b_s <= '1';

        wait for 10*clockPeriod;
        
        inicia_b_s <= '0';
        wait for 5*clockPeriod;
        inicia_b_s <= '1';

        wait for 10000*clockPeriod;

        reset_b_s <= '0';
        wait for 5*clockPeriod;
        reset_b_s <= '1';

        wait for 10*clockPeriod;

        inicia_b_s <= '0';
        wait for 5*clockPeriod;
        inicia_b_s <= '1';

        wait for 10*clockPeriod;

        para_b_s <= '0';
        wait for 5*clockPeriod;
        para_b_s <= '1';

        wait for 10*clockPeriod;

        reset_b_s <= '0';
        wait for 5*clockPeriod;
        reset_b_s <= '1';

        wait for 10*clockPeriod;


		clock_enable <= '0'; -- Desabilita clock		
		wait;  -- para a execução do simulador, caso contrário este process é reexecutado indefinidamente.
	end process;
end architecture;

projeto/simulacao_cronometro.vcd
$date
  Sat Jun 18 18:33:16 2022
$end
$version
  GHDL v0
$end
$timescale
  1 fs
$end
$scope module standard $end
$upscope $end
$scope module std_logic_1164 $end
$upscope $end
$scope module math_real $end
$upscope $end
$scope module numeric_std $end
$upscope $end
$scope module tb_cronometro $end
$var reg 1 ! clock_in $end
$var reg 1 " reset_in $end
$var reg 1 # clock_enable $end
$var reg 1 $ inicia_b_s $end
$var reg 1 % para_b_s $end
$var reg 1 & reset_b_s $end
$scope module dut $end
$var reg 1 ' inicia_b $end
$var reg 1 ( para_b $end
$var reg 1 ) reset_b $end
$var reg 1 * clock $end
$var reg 7 + display_0[6:0] $end
$var reg 7 , display_1[6:0] $end
$var reg 7 - display_2[6:0] $end
$var reg 7 . display_3[6:0] $end
$var reg 7 / display_4[6:0] $end
$var reg 7 0 display_5[6:0] $end
$var reg 4 1 q0_s[3:0] $end
$var reg 4 2 q1_s[3:0] $end
$var reg 4 3 q2_s[3:0] $end
$var reg 4 4 q3_s[3:0] $end
$var reg 4 5 q4_s[3:0] $end
$var reg 4 6 q5_s[3:0] $end
$var reg 1 7 ativado_s $end
$var reg 1 8 reset_s $end
$scope module fd $end
$var reg 1 9 clock $end
$var reg 1 : reset $end
$var reg 1 ; ativado $end
$var reg 4 < q0[3:0] $end
$var reg 4 = q1[3:0] $end
$var reg 4 > q2[3:0] $end
$var reg 4 ? q3[3:0] $end
$var reg 4 @ q4[3:0] $end
$var reg 4 A q5[3:0] $end
$var reg 7 B display_0[6:0] $end
$var reg 7 C display_1[6:0] $end
$var reg 7 D display_2[6:0] $end
$var reg 7 E display_3[6:0] $end
$var reg 7 F display_4[6:0] $end
$var reg 7 G display_5[6:0] $end
$var reg 4 H q0_s[3:0] $end
$var reg 4 I q1_s[3:0] $end
$var reg 4 J q2_s[3:0] $end
$var reg 4 K q3_s[3:0] $end
$var reg 4 L q4_s[3:0] $end
$var reg 4 M q5_s[3:0] $end
$var reg 1 N full0_s $end
$var reg 1 O full1_s $end
$var reg 1 P full2_s $end
$var reg 1 Q full3_s $end
$var reg 1 R full4_s $end
$var reg 1 S full5_s $end
$var reg 1 T clock_cont_0_s $end
$scope module cont_0 $end
$var reg 1 U clock $end
$var reg 4 V q[3:0] $end
$var reg 1 W full $end
$var reg 1 X reset $end
$var integer 32 Y q_integer_s $end
$var reg 1 Z full_s $end
$var reg 1 [ full_del_1_s $end
$var reg 1 \ full_out_s $end
$var reg 1 ] n_clock_s $end
$var reg 4 ^ q_s[3:0] $end
$scope module delay_reg_1 $end
$var reg 1 _ d $end
$var reg 1 ` clock $end
$var reg 1 a reset $end
$var reg 1 b preset $end
$var reg 1 c q $end
$var reg 1 d q_s $end
$upscope $end
$scope module delay_reg_2 $end
$var reg 1 e d $end
$var reg 1 f clock $end
$var reg 1 g reset $end
$var reg 1 h preset $end
$var reg 1 i q $end
$var reg 1 j q_s $end
$upscope $end
$upscope $end
$scope module cod_0 $end
$var reg 4 k entrada_bin[3:0] $end
$var reg 7 l saida_hexa[6:0] $end
$upscope $end
$scope module cont_1 $end
$var reg 1 m clock $end
$var reg 4 n q[3:0] $end
$var reg 1 o full $end
$var reg 1 p reset $end
$var integer 32 q q_integer_s $end
$var reg 1 r full_s $end
$var reg 1 s full_del_1_s $end
$var reg 1 t full_out_s $end
$var reg 1 u n_clock_s $end
$var reg 4 v q_s[3:0] $end
$scope module delay_reg_1 $end
$var reg 1 w d $end
$var reg 1 x clock $end
$var reg 1 y reset $end
$var reg 1 z preset $end
$var reg 1 { q $end
$var reg 1 | q_s $end
$upscope $end
$scope module delay_reg_2 $end
$var reg 1 } d $end
$var reg 1 !" clock $end
$var reg 1 "" reset $end
$var reg 1 #" preset $end
$var reg 1 $" q $end
$var reg 1 %" q_s $end
$upscope $end
$upscope $end
$scope module cod_1 $end
$var reg 4 &" entrada_bin[3:0] $end
$var reg 7 '" saida_hexa[6:0] $end
$upscope $end
$scope module cont_2 $end
$var reg 1 (" clock $end
$var reg 4 )" q[3:0] $end
$var reg 1 *" full $end
$var reg 1 +" reset $end
$var integer 32 ," q_integer_s $end
$var reg 1 -" full_s $end
$var reg 1 ." full_del_1_s $end
$var reg 1 /" full_out_s $end
$var reg 1 0" n_clock_s $end
$var reg 4 1" q_s[3:0] $end
$scope module delay_reg_1 $end
$var reg 1 2" d $end
$var reg 1 3" clock $end
$var reg 1 4" reset $end
$var reg 1 5" preset $end
$var reg 1 6" q $end
$var reg 1 7" q_s $end
$upscope $end
$scope module delay_reg_2 $end
$var reg 1 8" d $end
$var reg 1 9" clock $end
$var reg 1 :" reset $end
$var reg 1 ;" preset $end
$var reg 1 <" q $end
$var reg 1 =" q_s $end
$upscope $end
$upscope $end
$scope module cod_2 $end
$var reg 4 >" entrada_bin[3:0] $end
$var reg 7 ?" saida_hexa[6:0] $end
$upscope $end
$scope module cont_3 $end
$var reg 1 @" clock $end
$var reg 4 A" q[3:0] $end
$var reg 1 B" full $end
$var reg 1 C" reset $end
$var integer 32 D" q_integer_s $end
$var reg 1 E" full_s $end
$var reg 1 F" full_del_1_s $end
$var reg 1 G" full_out_s $end
$var reg 1 H" n_clock_s $end
$var reg 4 I" q_s[3:0] $end
$scope module delay_reg_1 $end
$var reg 1 J" d $end
$var reg 1 K" clock $end
$var reg 1 L" reset $end
$var reg 1 M" preset $end
$var reg 1 N" q $end
$var reg 1 O" q_s $end
$upscope $end
$scope module delay_reg_2 $end
$var reg 1 P" d $end
$var reg 1 Q" clock $end
$var reg 1 R" reset $end
$var reg 1 S" preset $end
$var reg 1 T" q $end
$var reg 1 U" q_s $end
$upscope $end
$upscope $end
$scope module cod_3 $end
$var reg 4 V" entrada_bin[3:0] $end
$var reg 7 W" saida_hexa[6:0] $end
$upscope $end
$scope module cont_4 $end
$var reg 1 X" clock $end
$var reg 4 Y" q[3:0] $end
$var reg 1 Z" full $end
$var reg 1 [" reset $end
$var integer 32 \" q_integer_s $end
$var reg 1 ]" full_s $end
$var reg 1 ^" full_del_1_s $end
$var reg 1 _" full_out_s $end
$var reg 1 `" n_clock_s $end
$var reg 4 a" q_s[3:0] $end
$scope module delay_reg_1 $end
$var reg 1 b" d $end
$var reg 1 c" clock $end
$var reg 1 d" reset $end
$var reg 1 e" preset $end
$var reg 1 f" q $end
$var reg 1 g" q_s $end
$upscope $end
$scope module delay_reg_2 $end
$var reg 1 h" d $end
$var reg 1 i" clock $end
$var reg 1 j" reset $end
$var reg 1 k" preset $end
$var reg 1 l" q $end
$var reg 1 m" q_s $end
$upscope $end
$upscope $end
$scope module cod_4 $end
$var reg 4 n" entrada_bin[3:0] $end
$var reg 7 o" saida_hexa[6:0] $end
$upscope $end
$scope module cont_5 $end
$var reg 1 p" clock $end
$var reg 4 q" q[3:0] $end
$var reg 1 r" full $end
$var reg 1 s" reset $end
$var integer 32 t" q_integer_s $end
$var reg 1 u" full_s $end
$var reg 1 v" full_del_1_s $end
$var reg 1 w" full_out_s $end
$var reg 1 x" n_clock_s $end
$var reg 4 y" q_s[3:0] $end
$scope module delay_reg_1 $end
$var reg 1 z" d $end
$var reg 1 {" clock $end
$var reg 1 |" reset $end
$var reg 1 }" preset $end
$var reg 1 !# q $end
$var reg 1 "# q_s $end
$upscope $end
$scope module delay_reg_2 $end
$var reg 1 ## d $end
$var reg 1 $# clock $end
$var reg 1 %# reset $end
$var reg 1 &# preset $end
$var reg 1 '# q $end
$var reg 1 (# q_s $end
$upscope $end
$upscope $end
$scope module cod_5 $end
$var reg 4 )# entrada_bin[3:0] $end
$var reg 7 *# saida_hexa[6:0] $end
$upscope $end
$upscope $end
$scope module uc $end
$var reg 1 +# inicia_b $end
$var reg 1 ,# para_b $end
$var reg 1 -# reset_b $end
$var reg 1 .# clock $end
$var reg 1 /# ativado $end
$var reg 1 0# reset $end
$comment currentstate is not handled $end
$comment nextstate is not handled $end
$upscope $end
$upscope $end
$upscope $end
$enddefinitions $end
#0
0!
0"
1#
1$
1%
1&
1'
1(
1)
0*
b0000001 +
b0000001 ,
b0000001 -
b0000001 .
b0000001 /
b0000001 0
b0000 1
b0000 2
b0000 3
b0000 4
b0000 5
b0000 6
07
18
09
1:
0;
b0000 <
b0000 =
b0000 >
b0000 ?
b0000 @
b0000 A
b0000001 B
b0000001 C
b0000001 D
b0000001 E
b0000001 F
b0000001 G
b0000 H
b0000 I
b0000 J
b0000 K
b0000 L
b0000 M
0N
0O
0P
0Q
0R
0S
0T
0U
b0000 V
0W
1X
b0 Y
0Z
0[
0\
1]
b0000 ^
0_
1`
1a
0b
0c
0d
0e
0f
1g
0h
0i
0j
b0000 k
b0000001 l
0m
b0000 n
0o
1p
b0 q
0r
0s
0t
1u
b0000 v
0w
1x
1y
0z
0{
0|
0}
0!"
1""
0#"
0$"
0%"
b0000 &"
b0000001 '"
0("
b0000 )"
0*"
1+"
b0 ,"
0-"
0."
0/"
10"
b0000 1"
02"
13"
14"
05"
06"
07"
08"
09"
1:"
0;"
0<"
0="
b0000 >"
b0000001 ?"
0@"
b0000 A"
0B"
1C"
b0 D"
0E"
0F"
0G"
1H"
b0000 I"
0J"
1K"
1L"
0M"
0N"
0O"
0P"
0Q"
1R"
0S"
0T"
0U"
b0000 V"
b0000001 W"
0X"
b0000 Y"
0Z"
1["
b0 \"
0]"
0^"
0_"
1`"
b0000 a"
0b"
1c"
1d"
0e"
0f"
0g"
0h"
0i"
1j"
0k"
0l"
0m"
b0000 n"
b0000001 o"
0p"
b0000 q"
0r"
1s"
b0 t"
0u"
0v"
0w"
1x"
b0000 y"
0z"
1{"
1|"
0}"
0!#
0"#
0##
0$#
1%#
0&#
0'#
0(#
b0000 )#
b0000001 *#
1+#
1,#
1-#
0.#
0/#
10#
#5000000000
1!
1*
08
19
0:
0X
0a
0g
0p
0y
0""
0+"
04"
0:"
0C"
0L"
0R"
0["
0d"
0j"
0s"
0|"
0%#
1.#
00#
#10000000000
0!
0*
09
0.#
#15000000000
1!
1*
19
1.#
#20000000000
0!
0*
09
0.#
#25000000000
1!
1*
19
1.#
#30000000000
0!
0*
09
0.#
#35000000000
1!
1*
19
1.#
#40000000000
0!
0*
09
0.#
#45000000000
1!
1*
19
1.#
#50000000000
0!
0*
09
0.#
#55000000000
1!
1*
19
1.#
#60000000000
0!
0*
09
0.#
#65000000000
1!
1*
19
1.#
#70000000000
0!
0*
09
0.#
#75000000000
1!
1*
19
1.#
#80000000000
0!
0*
09
0.#
#85000000000
1!
1*
19
1.#
#90000000000
0!
0*
09
0.#
#95000000000
1!
1*
19
1.#
#100000000000
0!
0*
09
0.#
#105000000000
1!
1*
19
1.#
#110000000000
0!
0*
09
0.#
#115000000000
1!
1*
19
1.#
#120000000000
0!
0*
09
0.#
#125000000000
1!
1*
19
1.#
#130000000000
0!
0*
09
0.#
#135000000000
1!
1*
19
1.#
#140000000000
0!
0*
09
0.#
#145000000000
1!
1*
19
1.#
#150000000000
0!
0*
09
0.#
#155000000000
1!
1*
19
1.#
#160000000000
0!
0*
09
0.#
#165000000000
1!
1*
19
1.#
#170000000000
0!
0*
09
0.#
#175000000000
1!
1*
19
1.#
#180000000000
0!
0*
09
0.#
#185000000000
1!
1*
19
1.#
#190000000000
0!
0*
09
0.#
#195000000000
1!
1*
19
1.#
#200000000000
0!
0$
0'
0*
09
0+#
0.#
#205000000000
1!
1*
b1001111 +
b0001 1
17
19
1;
b0001 <
b1001111 B
b0001 H
1T
1U
b0001 V
b1 Y
0]
b0001 ^
0`
1f
b0001 k
b1001111 l
1.#
1/#
#210000000000
0!
0*
09
0T
0U
1]
1`
0f
0.#
#215000000000
1!
1*
b0010010 +
b0010 1
19
b0010 <
b0010010 B
b0010 H
1T
1U
b0010 V
b10 Y
0]
b0010 ^
0`
1f
b0010 k
b0010010 l
1.#
#220000000000
0!
0*
09
0T
0U
1]
1`
0f
0.#
#225000000000
1!
1*
b0000110 +
b0011 1
19
b0011 <
b0000110 B
b0011 H
1T
1U
b0011 V
b11 Y
0]
b0011 ^
0`
1f
b0011 k
b0000110 l
1.#
#230000000000
0!
0*
09
0T
0U
1]
1`
0f
0.#
#235000000000
1!
1*
b1001100 +
b0100 1
19
b0100 <
b1001100 B
b0100 H
1T
1U
b0100 V
b100 Y
0]
b0100 ^
0`
1f
b0100 k
b1001100 l
1.#
#240000000000
0!
0*
09
0T
0U
1]
1`
0f
0.#
#245000000000
1!
1*
b0100100 +
b0101 1
19
b0101 <
b0100100 B
b0101 H
1T
1U
b0101 V
b101 Y
0]
b0101 ^
0`
1f
b0101 k
b0100100 l
1.#
#250000000000
0!
1$
1'
0*
09
0T
0U
1]
1`
0f
1+#
0.#
#255000000000
1!
1*
b0100000 +
b0110 1
19
b0110 <
b0100000 B
b0110 H
1T
1U
b0110 V
b110 Y
0]
b0110 ^
0`
1f
b0110 k
b0100000 l
1.#
#260000000000
0!
0*
09
0T
0U
1]
1`
0f
0.#
#265000000000
1!
1*
b0001111 +
b0111 1
19
b0111 <
b0001111 B
b0111 H
1T
1U
b0111 V
b111 Y
0]
b0111 ^
0`
1f
b0111 k
b0001111 l
1.#
#270000000000
0!
0*
09
0T
0U
1]
1`
0f
0.#
#275000000000
1!
1*
b0000000 +
b1000 1
19
b1000 <
b0000000 B
b1000 H
1T
1U
b1000 V
b1000 Y
0]
b1000 ^
0`
1f
b1000 k
b0000000 l
1.#
#280000000000
0!
0*
09
0T
0U
1]
1`
0f
0.#
#285000000000
1!
1*
b0001100 +
b1001 1
19
b1001 <
b0001100 B
b1001 H
1T
1U
b1001 V
b1001 Y
1Z
0]
b1001 ^
1_
0`
1f
b1001 k
b0001100 l
1.#
#290000000000
0!
0*
09
0T
0U
1[
1]
1`
1c
1d
1e
0f
0.#
#295000000000
1!
1*
b0000001 +
b1001111 ,
b0000 1
b0001 2
19
b0000 <
b0001 =
b0000001 B
b1001111 C
b0000 H
b0001 I
1N
1T
1U
b0000 V
1W
b0 Y
0Z
1\
0]
b0000 ^
0_
0`
1f
1i
1j
b0000 k
b0000001 l
1m
b0001 n
b1 q
0u
b0001 v
0x
1!"
b0001 &"
b1001111 '"
1.#
#300000000000
0!
0*
09
0T
0U
0[
1]
1`
0c
0d
0e
0f
0.#
#305000000000
1!
1*
b1001111 +
b0001 1
19
b0001 <
b1001111 B
b0001 H
0N
1T
1U
b0001 V
0W
b1 Y
0\
0]
b0001 ^
0`
1f
0i
0j
b0001 k
b1001111 l
0m
1u
1x
0!"
1.#
#310000000000
0!
0*
09
0T
0U
1]
1`
0f
0.#
#315000000000
1!
1*
b0010010 +
b0010 1
19
b0010 <
b0010010 B
b0010 H
1T
1U
b0010 V
b10 Y
0]
b0010 ^
0`
1f
b0010 k
b0010010 l
1.#
#320000000000
0!
0*
09
0T
0U
1]
1`
0f
0.#
#325000000000
1!
1*
b0000110 +
b0011 1
19
b0011 <
b0000110 B
b0011 H
1T
1U
b0011 V
b11 Y
0]
b0011 ^
0`
1f
b0011 k
b0000110 l
1.#
#330000000000
0!
0*
09
0T
0U
1]
1`
0f
0.#
#335000000000
1!
1*
b1001100 +
b0100 1
19
b0100 <
b1001100 B
b0100 H
1T
1U
b0100 V
b100 Y
0]
b0100 ^
0`
1f
b0100 k
b1001100 l
1.#
#340000000000
0!
0*
09
0T
0U
1]
1`
0f
0.#
#345000000000
1!
1*
b0100100 +
b0101 1
19
b0101 <
b0100100 B
b0101 H
1T
1U
b0101 V
b101 Y
0]
b0101 ^
0`
1f
b0101 k
b0100100 l
1.#
#350000000000
0!
0%
0(
0*
09
0T
0U
1]
1`
0f
0,#
0.#
#355000000000
1!
1*
b0100000 +
b0110 1
07
19
0;
b0110 <
b0100000 B
b0110 H
0T
0U
b0110 V
b110 Y
1]
b0110 ^
1`
0f
b0110 k
b0100000 l
1.#
0/#
#360000000000
0!
0*
09
0.#
#365000000000
1!
1*
19
1.#
#370000000000
0!
0*
09
0.#
#375000000000
1!
1*
19
1.#
#380000000000
0!
0*
09
0.#
#385000000000
1!
1*
19
1.#
#390000000000
0!
0*
09
0.#
#395000000000
1!
1*
19
1.#
#400000000000
0!
1%
1(
0*
09
1,#
0.#
#405000000000
1!
1*
19
1.#
#410000000000
0!
0*
09
0.#
#415000000000
1!
1*
19
1.#
#420000000000
0!
0*
09
0.#
#425000000000
1!
1*
19
1.#
#430000000000
0!
0*
09
0.#
#435000000000
1!
1*
19
1.#
#440000000000
0!
0*
09
0.#
#445000000000
1!
1*
19
1.#
#450000000000
0!
0*
09
0.#
#455000000000
1!
1*
19
1.#
#460000000000
0!
0*
09
0.#
#465000000000
1!
1*
19
1.#
#470000000000
0!
0*
09
0.#
#475000000000
1!
1*
19
1.#
#480000000000
0!
0*
09
0.#
#485000000000
1!
1*
19
1.#
#490000000000
0!
0*
09
0.#
#495000000000
1!
1*
19
1.#
#500000000000
0!
0$
0'
0*
09
0+#
0.#
#505000000000
1!
1*
b0001111 +
b0111 1
17
19
1;
b0111 <
b0001111 B
b0111 H
1T
1U
b0111 V
b111 Y
0]
b0111 ^
0`
1f
b0111 k
b0001111 l
1.#
1/#
#510000000000
0!
0*
09
0T
0U
1]
1`
0f
0.#
#515000000000
1!
1*
b0000000 +
b1000 1
19
b1000 <
b0000000 B
b1000 H
1T
1U
b1000 V
b1000 Y
0]
b1000 ^
0`
1f
b1000 k
b0000000 l
1.#
#520000000000
0!
0*
09
0T
0U
1]
1`
0f
0.#
#525000000000
1!
1*
b0001100 +
b1001 1
19
b1001 <
b0001100 B
b1001 H
1T
1U
b1001 V
b1001 Y
1Z
0]
b1001 ^
1_
0`
1f
b1001 k
b0001100 l
1.#
#530000000000
0!
0*
09
0T
0U
1[
1]
1`
1c
1d
1e
0f
0.#
