projeto/unidade_de_controle.vhd
-- library declaration
library IEEE;
use IEEE.std_logic_1164.all;

-- entity
entity unidade_de_controle is 
    port(
        inicia_b, para_b, reset_b : in std_logic;
        clock: in  std_logic;
        ativado, reset : out std_logic
    );
end unidade_de_controle;

-- architecture
architecture arch of unidade_de_controle is
    type state_type is (zera, parado, contando);
    signal CurrentState, NextState : state_type;
begin  
    update_state: process (clock, reset_b) --talvez dê errado
    begin
        if (reset_b = '0') then
            CurrentState <= zera;
        elsif (rising_edge(clock)) then 
            CurrentState <= NextState;
        end if;
    end process update_state;
    
    update_output: process (CurrentState)
    begin
        case CurrentState is 
            when zera =>
                ativado <= '0';
                reset <= '1';
            when parado =>
                ativado <= '0';
                reset <= '0';
            when contando => 
                ativado <= '1';
                reset <= '0';
            end case;
        end process update_output;

    update_next_state: process(inicia_b, para_b, reset_b)
    begin
        case CurrentState is 
            when zera =>
                NextState <= parado;
            when parado =>
                if inicia_b = '0' then
                    NextState <= contando;
                else 
                    NextState <= parado;
                end if;
            when contando => 
                if para_b = '0' then
                    NextState <= parado;
                else
                    NextState <= contando;
                end if;
        end case;
    end process update_next_state;
end arch;

projeto/tb_unidade_de_controle.vhd
library ieee;
use IEEE.STD_LOGIC_1164.ALL;
use ieee.math_real.ceil;
use ieee.math_real.log2;
use ieee.numeric_std.all;
entity tb_unidade_de_controle is
end tb_unidade_de_controle;

architecture tb_unidade_de_controle_arch of tb_unidade_de_controle is


component unidade_de_controle is 
    port(
        inicia_b, para_b, reset_b : std_logic;
        clock: in  std_logic;
        ativado, reset : out std_logic
    );
end component;

	

	signal clock_in: std_logic := '0';
	signal reset_in: std_logic := '0';
	constant clockPeriod: time := 2 ns; -- periodo do clock
	signal clock_enable : std_logic := '0';

    signal inicia_b_s, para_b_s, reset_b_s : std_logic := '1';
    signal ativado_s, reset_s : STD_LOGIC := '0';
begin
	DUT: unidade_de_controle
    port map(
        inicia_b => inicia_b_s,
        para_b => para_b_s,
        reset_b => reset_b_s,
        clock => clock_in,
        reset => reset_s,
        ativado => ativado_s
    );
	
    clock_in <= (clock_enable and (not clock_in)) after clockPeriod/2;
	
	estimulos: process is
	begin
        clock_enable <= '1';
        wait for 20*clockPeriod;

        inicia_b_s <= '0';
        wait for 5*clockPeriod;
        inicia_b_s <= '1';

        wait for 10*clockPeriod;

        para_b_s <= '0';
        wait for 5*clockPeriod;
        para_b_s <= '1';

        wait for 10*clockPeriod;
        
        inicia_b_s <= '0';
        wait for 5*clockPeriod;
        inicia_b_s <= '1';

        wait for 10*clockPeriod;

        reset_b_s <= '0';
        wait for 5*clockPeriod;
        reset_b_s <= '1';

        wait for 10*clockPeriod;

        inicia_b_s <= '0';
        wait for 5*clockPeriod;
        inicia_b_s <= '1';

        wait for 10*clockPeriod;

        para_b_s <= '0';
        wait for 5*clockPeriod;
        para_b_s <= '1';

        wait for 10*clockPeriod;

        reset_b_s <= '0';
        wait for 5*clockPeriod;
        reset_b_s <= '1';

        wait for 10*clockPeriod;


		clock_enable <= '0'; -- Desabilita clock		
		wait;  -- para a execução do simulador, caso contrário este process é reexecutado indefinidamente.
	end process;
end architecture;

projeto/simul_UC.vcd
$date
  Sat Jun 18 19:41:17 2022
$end
$version
  GHDL v0
$end
$timescale
  1 fs
$end
$scope module standard $end
$upscope $end
$scope module std_logic_1164 $end
$upscope $end
$scope module math_real $end
$upscope $end
$scope module numeric_std $end
$upscope $end
$scope module tb_unidade_de_controle $end
$var reg 1 ! clock_in $end
$var reg 1 " reset_in $end
$var reg 1 # clock_enable $end
$var reg 1 $ inicia_b_s $end
$var reg 1 % para_b_s $end
$var reg 1 & reset_b_s $end
$var reg 1 ' ativado_s $end
$var reg 1 ( reset_s $end
$scope module dut $end
$var reg 1 ) inicia_b $end
$var reg 1 * para_b $end
$var reg 1 + reset_b $end
$var reg 1 , clock $end
$var reg 1 - ativado $end
$var reg 1 . reset $end
$comment currentstate is not handled $end
$comment nextstate is not handled $end
$upscope $end
$upscope $end
$enddefinitions $end
#0
0!
0"
1#
1$
1%
1&
0'
1(
1)
1*
1+
0,
0-
1.
#1000000
1!
0(
1,
0.
#2000000
0!
0,
#3000000
1!
1,
#4000000
0!
0,
#5000000
1!
1,
#6000000
0!
0,
#7000000
1!
1,
#8000000
0!
0,
#9000000
1!
1,
#10000000
0!
0,
#11000000
1!
1,
#12000000
0!
0,
#13000000
1!
1,
#14000000
0!
0,
#15000000
1!
1,
#16000000
0!
0,
#17000000
1!
1,
#18000000
0!
0,
#19000000
1!
1,
#20000000
0!
0,
#21000000
1!
1,
#22000000
0!
0,
#23000000
1!
1,
#24000000
0!
0,
#25000000
1!
1,
#26000000
0!
0,
#27000000
1!
1,
#28000000
0!
0,
#29000000
1!
1,
#30000000
0!
0,
#31000000
1!
1,
#32000000
0!
0,
#33000000
1!
1,
#34000000
0!
0,
#35000000
1!
1,
#36000000
0!
0,
#37000000
1!
1,
#38000000
0!
0,
#39000000
1!
1,
#40000000
0!
0$
0)
0,
#41000000
1!
1'
1,
1-
#42000000
0!
0,
#43000000
1!
1,
#44000000
0!
0,
#45000000
1!
1,
#46000000
0!
0,
#47000000
1!
1,
#48000000
0!
0,
#49000000
1!
1,
#50000000
0!
1$
1)
0,
#51000000
1!
1,
#52000000
0!
0,
#53000000
1!
1,
#54000000
0!
0,
#55000000
1!
1,
#56000000
0!
0,
#57000000
1!
1,
#58000000
0!
0,
#59000000
1!
1,
#60000000
0!
0,
#61000000
1!
1,
#62000000
0!
0,
#63000000
1!
1,
#64000000
0!
0,
#65000000
1!
1,
#66000000
0!
0,
#67000000
1!
1,
#68000000
0!
0,
#69000000
1!
1,
#70000000
0!
0%
0*
0,
#71000000
1!
0'
1,
0-
#72000000
0!
0,
#73000000
1!
1,
#74000000
0!
0,
#75000000
1!
1,
#76000000
0!
0,
#77000000
1!
1,
#78000000
0!
0,
#79000000
1!
1,
#80000000
0!
1%
1*
0,
#81000000
1!
1,
#82000000
0!
0,
#83000000
1!
1,
#84000000
0!
0,
#85000000
1!
1,
#86000000
0!
0,
#87000000
1!
1,
#88000000
0!
0,
#89000000
1!
1,
#90000000
0!
0,
#91000000
1!
1,
#92000000
0!
0,
#93000000
1!
1,
#94000000
0!
0,
#95000000
1!
1,
#96000000
0!
0,
#97000000
1!
1,
#98000000
0!
0,
#99000000
1!
1,
#100000000
0!
0$
0)
0,
#101000000
1!
1'
1,
1-
#102000000
0!
0,
#103000000
1!
1,
#104000000
0!
0,
#105000000
1!
1,
#106000000
0!
0,
#107000000
1!
1,
#108000000
0!
0,
#109000000
1!
1,
#110000000
0!
1$
1)
0,
#111000000
1!
1,
#112000000
0!
0,
#113000000
1!
1,
#114000000
0!
0,
#115000000
1!
1,
#116000000
0!
0,
#117000000
1!
1,
#118000000
0!
0,
#119000000
1!
1,
#120000000
0!
0,
#121000000
1!
1,
#122000000
0!
0,
#123000000
1!
1,
#124000000
0!
0,
#125000000
1!
1,
#126000000
0!
0,
#127000000
1!
1,
#128000000
0!
0,
#129000000
1!
1,
#130000000
0!
0&
0'
1(
0+
0,
0-
1.
#131000000
1!
1,
#132000000
0!
0,
#133000000
1!
1,
#134000000
0!
0,
#135000000
1!
1,
#136000000
0!
0,
#137000000
1!
1,
#138000000
0!
0,
#139000000
1!
1,
#140000000
0!
1&
1+
0,
#141000000
1!
0(
1,
0.
#142000000
0!
0,
#143000000
1!
1,
#144000000
0!
0,
#145000000
1!
1,
#146000000
0!
0,
#147000000
1!
1,
#148000000
0!
0,
#149000000
1!
1,
#150000000
0!
0,
#151000000
1!
1,
#152000000
0!
0,
#153000000
1!
1,
#154000000
0!
0,
#155000000
1!
1,
#156000000
0!
0,
#157000000
1!
1,
#158000000
0!
0,
#159000000
1!
1,
#160000000
0!
0$
0)
0,
#161000000
1!
1'
1,
1-
#162000000
0!
0,
#163000000
1!
1,
#164000000
0!
0,
#165000000
1!
1,
#166000000
0!
0,
#167000000
1!
1,
#168000000
0!
0,
#169000000
1!
1,
#170000000
0!
1$
1)
0,
#171000000
1!
1,
#172000000
0!
0,
#173000000
1!
1,
#174000000
0!
0,
#175000000
1!
1,
#176000000
0!
0,
#177000000
1!
1,
#178000000
0!
0,
#179000000
1!
1,
#180000000
0!
0,
#181000000
1!
1,
#182000000
0!
0,
#183000000
1!
1,
#184000000
0!
0,
#185000000
1!
1,
#186000000
0!
0,
#187000000
1!
1,
#188000000
0!
0,
#189000000
1!
1,
#190000000
0!
0%
0*
0,
#191000000
1!
0'
1,
0-
#192000000
0!
0,
#193000000
1!
1,
#194000000
0!
0,
#195000000
1!
1,
#196000000
0!
0,
#197000000
1!
1,
#198000000
0!
0,
#199000000
1!
1,
#200000000
0!
1%
1*
0,
#201000000
1!
1,
#202000000
0!
0,
#203000000
1!
1,
#204000000
0!
0,
#205000000
1!
1,
#206000000
0!
0,
#207000000
1!
1,
#208000000
0!
0,
#209000000
1!
1,
#210000000
0!
0,
#211000000
1!
1,
#212000000
0!
0,
#213000000
1!
1,
#214000000
0!
0,
#215000000
1!
1,
#216000000
0!
0,
#217000000
1!
1,
#218000000
0!
0,
#219000000
1!
1,
#220000000
0!
0&
1(
0+
0,
1.
#221000000
1!
1,
#222000000
0!
0,
#223000000
1!
1,
#224000000
0!
0,
#225000000
1!
1,
#226000000
0!
0,
#227000000
1!
1,
#228000000
0!
0,
#229000000
1!
1,
#230000000
0!
1&
1+
0,
#231000000
1!
0(
1,
0.
