P2/comparador.vhd
library IEEE;
use IEEE.STD_LOGIC_1164.ALL;
use ieee.numeric_std.all;

entity comparador IS 
    port(
        A, B : in std_logic_vector(3 downto 0);
        AeB, AgB, AlB : out std_logic
    );
end comparador;

architecture comparador_arch of comparador is

signal A_s, B_s : integer range 0 to 15 := 0;
signal AeB_s, AgB_s, AlB_s : std_logic;

begin

    A_s <= to_integer(unsigned(A));
    B_s <= to_integer(unsigned(B));


    AeB_s <= '1' when A_s = B_s else '0';
    AgB_s <= '1' when A_s > B_s else '0';
    AlB_s <= '1' when A_s < B_s else '0';

    AeB <= AeB_s after 5 ns;
    AgB <= AgB_s after 5 ns;
    AlB <= AlB_s after 5 ns;
end architecture;

P2/contador.vhd
library IEEE;
use IEEE.STD_LOGIC_1164.ALL;
use ieee.numeric_std.all;

entity contador IS 
    generic(
        max : integer := 15
    );
    port(
        clock : in std_logic; --active HIGH
        load_n : in  std_logic; --active LOW
        Q_in : in std_logic_vector(3 downto 0);
        Q : out std_logic_vector(3 downto 0);
        reset_n : in std_logic
    );
end contador;

architecture contador_arch of contador is

signal Q_integer_s :  integer range 0 to 15 := 0;
signal Q_s : std_logic_vector(3 downto 0) := "0000";

begin
    process(clock, reset_n, Q_integer_s, load_n)
    begin
        if rising_edge(clock) then
            if reset_n = '0' then -- active low
                Q_integer_s <= 0;
            elsif load_n = '0' then --active low
                Q_integer_s <= to_integer(unsigned(Q_in));
            elsif Q_integer_s = max then 
                Q_integer_s <= 0;
            elsif Q_integer_s < max then
                Q_integer_s <= Q_integer_s + 1;
            end if;
        end if;
    end process;

    Q_s <= std_logic_vector(to_unsigned(Q_integer_s, Q_s'length));
    Q <= Q_s;
end architecture;

P2/fluxo_de_Dados.vhd
library IEEE;
use IEEE.STD_LOGIC_1164.ALL;
use ieee.numeric_std.all;

entity fluxo_de_dados IS 
    generic(
        max : integer := 15
    );
    port(
        clock : in std_logic;
        grava, conta, zera : in std_logic;
        Q0_in, Q1_in, Q2_in, Q3_in : in std_logic_vector(3 downto 0);
        Q0_out, Q1_out, Q2_out, Q3_out : out std_logic_vector(3 downto 0)
    );
end fluxo_de_dados;

architecture fluxo_de_dados_arch of fluxo_de_dados is

component contador IS 
    generic(
        max : integer := 15
    );
    port(
        clock : in std_logic;
        load_n : in std_logic;
        Q_in : in std_logic_vector(3 downto 0);
        Q : out std_logic_vector(3 downto 0);
        reset_n : in std_logic
    );
end component;

component comparador IS 
    port(
        A, B : in std_logic_vector(3 downto 0);
        AeB, AgB, AlB : out std_logic
    );
end component;

signal clock0_s, clock1_s, clock2_s, clock3_s: std_logic;
signal reset_s, grava_s : std_logic;
signal reset_0_s, reset_1_s, reset_2_s, reset_3_s : std_logic := '1';
signal f_0, f_1, f_2, f_3 : std_logic;
signal Q0_s, Q1_s, Q2_s, Q3_s : std_logic_vector(3 downto 0);
signal Q0_in_s, Q1_in_s, Q2_in_s, Q3_in_s : std_logic_vector(3 downto 0);

begin

    cont_0 : contador port map(
        clock => clock0_s,
        Q => Q0_s,
        Q_in => Q0_in_s,
        load_n => grava_s,
        reset_n => reset_0_s
    );

    comp_0 : comparador port map(
        A => Q0_s,
        B => "1001",
        AeB => f_0
    );

    cont_1 : contador port map(
        clock => clock1_s,
        Q => Q1_s,
        Q_in => Q1_in,
        load_n => grava_s,
        reset_n => reset_1_s
    );

    comp_1 : comparador port map(
        A => Q1_s,
        B => "1001",
        AeB => f_1
    );

    cont_2 : contador port map(
        clock => clock2_s,
        Q => Q2_s,
        Q_in => Q2_in,
        load_n => grava_s,
        reset_n => reset_2_s
    );

    comp_2 : comparador port map(
        A => Q2_s,
        B => "1001",
        AeB => f_2
    );

    cont_3 : contador port map(
        clock => clock3_s,
        Q => Q3_s,
        Q_in => Q3_in,
        load_n => grava_s,
        reset_n => reset_3_s
    );

    comp_3 : comparador port map(
        A => Q3_s,
        B => "1001",
        AeB => f_3
    );



    clock0_s <= (clock and conta) or reset_s;
    clock1_s <= (clock0_s and f_0) or reset_s;
    clock2_s <= (clock1_s and f_1) or reset_s;
    clock3_s <= (clock2_s and f_2) or reset_s;

    reset_0_s <= not(reset_s or f_0);
    reset_1_s <= not(reset_s or f_1);
    reset_2_s <= not(reset_s or f_2);
    reset_3_s <= not(reset_s or f_3);

    Q0_out <= Q0_s;
    Q1_out <= Q1_s;
    Q2_out <= Q2_s;
    Q3_out <= Q3_s;

    reset_s <= zera;
    grava_s <= grava;

end architecture;

P2/tb_fluxo_de_dados.vhd
library ieee;
use IEEE.STD_LOGIC_1164.ALL;
use ieee.math_real.ceil;
use ieee.math_real.log2;
use ieee.numeric_std.all;
entity tb_fluxo_de_dados is
end tb_fluxo_de_dados;

architecture tb_fluxo_de_dados_arch of tb_fluxo_de_dados is


component fluxo_de_dados IS 
    generic(
        max : integer := 15
    );
    port(
        clock : in std_logic;
        grava, conta, zera : in std_logic;
        Q0_in, Q1_in, Q2_in, Q3_in : in std_logic_vector(3 downto 0);
        Q0_out, Q1_out, Q2_out, Q3_out : out std_logic_vector(3 downto 0)
    );
end component;

	
	signal clock_in: std_logic := '0';
	signal clock_enable : std_logic := '0';
	constant clockPeriod: time := 10 us; -- periodo do clock

	signal grava_s, conta_s, zera_s: std_logic := '0';
	signal Q0_in_s, Q1_in_s, Q2_in_s, Q3_in_s: std_logic_vector(3 downto 0) := "0000";
	signal Q0_out_s, Q1_out_s, Q2_out_s, Q3_out_s: std_logic_vector(3 downto 0);
    

begin
	DUT: fluxo_de_dados port map(
        clock => clock_in,
        grava => grava_s,
        conta => conta_s,
        zera => zera_s,
        Q0_in => Q0_in_s,
        Q1_in => Q1_in_s,
        Q2_in => Q2_in_s,
        Q3_in => Q3_in_s,
        Q0_out => Q0_out_s,
        Q1_out => Q1_out_s,
        Q2_out => Q2_out_s,
        Q3_out => Q3_out_s
    );
	
    clock_in <= (clock_enable and (not clock_in)) after clockPeriod/2;
	
	estimulos: process is
	begin
        clock_enable <= '1';
        wait for 20*clockPeriod;

        grava_s <= '1';
        conta_s <= '0';
        zera_s <= '0';
        wait for 20*clockPeriod;

        -- Conta 70
        grava_s <= '1';
        conta_s <= '1';
        zera_s <= '0';
        wait for 70*clockPeriod;

        -- zera
        grava_s <= '1';
        conta_s <= '1';
        zera_s <= '1';
        wait for 20*clockPeriod;

        -- conta 20
        grava_s <= '1';
        conta_s <= '1';
        zera_s <= '0';
        wait for 20*clockPeriod;

        -- para de contar
        grava_s <= '1';
        conta_s <= '0';
        zera_s <= '0';
        wait for 20*clockPeriod;

        -- conta 20
        grava_s <= '1';
        conta_s <= '1';
        zera_s <= '0';
        wait for 20*clockPeriod;

        -- grava o numero
        Q0_in_s <= "0011";
        Q1_in_s <= "0011";
        Q2_in_s <= "0011";
        Q3_in_s <= "0011";
        grava_s <= '0';
        conta_s <= '1';
        zera_s <= '0';
        wait for 20*clockPeriod;

		clock_enable <= '0'; -- Desabilita clock		
		wait;  -- para a execução do simulador, caso contrário este process é reexecutado indefinidamente.
	end process;
end architecture;

P2/simul_fluxo_de_dados.vcd
$date
  Mon Jul 18 13:04:32 2022
$end
$version
  GHDL v0
$end
$timescale
  1 fs
$end
$scope module standard $end
$upscope $end
$scope module std_logic_1164 $end
$upscope $end
$scope module math_real $end
$upscope $end
$scope module numeric_std $end
$upscope $end
$scope module tb_fluxo_de_dados $end
$var reg 1 ! clock_in $end
$var reg 1 " clock_enable $end
$var reg 1 # grava_s $end
$var reg 1 $ conta_s $end
$var reg 1 % zera_s $end
$var reg 4 & q0_in_s[3:0] $end
$var reg 4 ' q1_in_s[3:0] $end
$var reg 4 ( q2_in_s[3:0] $end
$var reg 4 ) q3_in_s[3:0] $end
$var reg 4 * q0_out_s[3:0] $end
$var reg 4 + q1_out_s[3:0] $end
$var reg 4 , q2_out_s[3:0] $end
$var reg 4 - q3_out_s[3:0] $end
$scope module dut $end
$var reg 1 . clock $end
$var reg 1 / grava $end
$var reg 1 0 conta $end
$var reg 1 1 zera $end
$var reg 4 2 q0_in[3:0] $end
$var reg 4 3 q1_in[3:0] $end
$var reg 4 4 q2_in[3:0] $end
$var reg 4 5 q3_in[3:0] $end
$var reg 4 6 q0_out[3:0] $end
$var reg 4 7 q1_out[3:0] $end
$var reg 4 8 q2_out[3:0] $end
$var reg 4 9 q3_out[3:0] $end
$var reg 1 : clock0_s $end
$var reg 1 ; clock1_s $end
$var reg 1 < clock2_s $end
$var reg 1 = clock3_s $end
$var reg 1 > reset_s $end
$var reg 1 ? grava_s $end
$var reg 1 @ reset_0_s $end
$var reg 1 A reset_1_s $end
$var reg 1 B reset_2_s $end
$var reg 1 C reset_3_s $end
$var reg 1 D f_0 $end
$var reg 1 E f_1 $end
$var reg 1 F f_2 $end
$var reg 1 G f_3 $end
$var reg 4 H q0_s[3:0] $end
$var reg 4 I q1_s[3:0] $end
$var reg 4 J q2_s[3:0] $end
$var reg 4 K q3_s[3:0] $end
$var reg 4 L q0_in_s[3:0] $end
$var reg 4 M q1_in_s[3:0] $end
$var reg 4 N q2_in_s[3:0] $end
$var reg 4 O q3_in_s[3:0] $end
$scope module cont_0 $end
$var reg 1 P clock $end
$var reg 1 Q load_n $end
$var reg 4 R q_in[3:0] $end
$var reg 4 S q[3:0] $end
$var reg 1 T reset_n $end
$var integer 32 U q_integer_s $end
$var reg 4 V q_s[3:0] $end
$upscope $end
$scope module comp_0 $end
$var reg 4 W a[3:0] $end
$var reg 4 X b[3:0] $end
$var reg 1 Y aeb $end
$var reg 1 Z agb $end
$var reg 1 [ alb $end
$var integer 32 \ a_s $end
$var integer 32 ] b_s $end
$var reg 1 ^ aeb_s $end
$var reg 1 _ agb_s $end
$var reg 1 ` alb_s $end
$upscope $end
$scope module cont_1 $end
$var reg 1 a clock $end
$var reg 1 b load_n $end
$var reg 4 c q_in[3:0] $end
$var reg 4 d q[3:0] $end
$var reg 1 e reset_n $end
$var integer 32 f q_integer_s $end
$var reg 4 g q_s[3:0] $end
$upscope $end
$scope module comp_1 $end
$var reg 4 h a[3:0] $end
$var reg 4 i b[3:0] $end
$var reg 1 j aeb $end
$var reg 1 k agb $end
$var reg 1 l alb $end
$var integer 32 m a_s $end
$var integer 32 n b_s $end
$var reg 1 o aeb_s $end
$var reg 1 p agb_s $end
$var reg 1 q alb_s $end
$upscope $end
$scope module cont_2 $end
$var reg 1 r clock $end
$var reg 1 s load_n $end
$var reg 4 t q_in[3:0] $end
$var reg 4 u q[3:0] $end
$var reg 1 v reset_n $end
$var integer 32 w q_integer_s $end
$var reg 4 x q_s[3:0] $end
$upscope $end
$scope module comp_2 $end
$var reg 4 y a[3:0] $end
$var reg 4 z b[3:0] $end
$var reg 1 { aeb $end
$var reg 1 | agb $end
$var reg 1 } alb $end
$var integer 32 !" a_s $end
$var integer 32 "" b_s $end
$var reg 1 #" aeb_s $end
$var reg 1 $" agb_s $end
$var reg 1 %" alb_s $end
$upscope $end
$scope module cont_3 $end
$var reg 1 &" clock $end
$var reg 1 '" load_n $end
$var reg 4 (" q_in[3:0] $end
$var reg 4 )" q[3:0] $end
$var reg 1 *" reset_n $end
$var integer 32 +" q_integer_s $end
$var reg 4 ," q_s[3:0] $end
$upscope $end
$scope module comp_3 $end
$var reg 4 -" a[3:0] $end
$var reg 4 ." b[3:0] $end
$var reg 1 /" aeb $end
$var reg 1 0" agb $end
$var reg 1 1" alb $end
$var integer 32 2" a_s $end
$var integer 32 3" b_s $end
$var reg 1 4" aeb_s $end
$var reg 1 5" agb_s $end
$var reg 1 6" alb_s $end
$upscope $end
$upscope $end
$upscope $end
$enddefinitions $end
#0
0!
1"
0#
0$
0%
b0000 &
b0000 '
b0000 (
b0000 )
b0000 *
b0000 +
b0000 ,
b0000 -
0.
0/
00
01
b0000 2
b0000 3
b0000 4
b0000 5
b0000 6
b0000 7
b0000 8
b0000 9
0:
0;
0<
0=
0>
0?
U@
UA
UB
UC
UD
UE
UF
UG
b0000 H
b0000 I
b0000 J
b0000 K
bUUUU L
bUUUU M
bUUUU N
bUUUU O
0P
0Q
bUUUU R
b0000 S
UT
b0 U
b0000 V
b0000 W
b0000 X
UY
UZ
U[
b0 \
b0 ]
1^
0_
0`
0a
0b
b0000 c
b0000 d
Ue
b0 f
b0000 g
b0000 h
b0000 i
Uj
Uk
Ul
b0 m
b0 n
1o
0p
0q
0r
0s
b0000 t
b0000 u
Uv
b0 w
b0000 x
b0000 y
b1001 z
U{
U|
U}
b0 !"
b1001 ""
0#"
0$"
1%"
0&"
0'"
b0000 ("
b0000 )"
U*"
b0 +"
b0000 ,"
b0000 -"
b1001 ."
U/"
U0"
U1"
b0 2"
b1001 3"
04"
05"
16"
#5000000
0@
0A
1B
1C
1D
1E
0F
0G
0T
1Y
0Z
0[
0e
1j
0k
0l
1v
0{
0|
1}
1*"
0/"
00"
11"
#5000000000
1!
1.
#10000000000
0!
0.
#15000000000
1!
1.
#20000000000
0!
0.
#25000000000
1!
1.
#30000000000
0!
0.
#35000000000
1!
1.
#40000000000
0!
0.
#45000000000
1!
1.
#50000000000
0!
0.
#55000000000
1!
1.
#60000000000
0!
0.
#65000000000
1!
1.
#70000000000
0!
0.
#75000000000
1!
1.
#80000000000
0!
0.
#85000000000
1!
1.
#90000000000
0!
0.
#95000000000
1!
1.
#100000000000
0!
0.
#105000000000
1!
1.
#110000000000
0!
0.
#115000000000
1!
1.
#120000000000
0!
0.
#125000000000
1!
1.
#130000000000
0!
0.
#135000000000
1!
1.
#140000000000
0!
0.
#145000000000
1!
1.
#150000000000
0!
0.
#155000000000
1!
1.
#160000000000
0!
0.
#165000000000
1!
1.
#170000000000
0!
0.
#175000000000
1!
1.
#180000000000
0!
0.
#185000000000
1!
1.
#190000000000
0!
0.
#195000000000
1!
1.
#200000000000
0!
1#
0.
1/
1?
1Q
1b
1s
1'"
#205000000000
1!
1.
#210000000000
0!
0.
#215000000000
1!
1.
#220000000000
0!
0.
#225000000000
1!
1.
#230000000000
0!
0.
#235000000000
1!
1.
#240000000000
0!
0.
#245000000000
1!
1.
#250000000000
0!
0.
#255000000000
1!
1.
#260000000000
0!
0.
#265000000000
1!
1.
#270000000000
0!
0.
#275000000000
1!
1.
#280000000000
0!
0.
#285000000000
1!
1.
#290000000000
0!
0.
#295000000000
1!
1.
#300000000000
0!
0.
#305000000000
1!
1.
#310000000000
0!
0.
#315000000000
1!
1.
#320000000000
0!
0.
#325000000000
1!
1.
#330000000000
0!
0.
#335000000000
1!
1.
#340000000000
0!
0.
#345000000000
1!
1.
#350000000000
0!
0.
#355000000000
1!
1.
#360000000000
0!
0.
#365000000000
1!
1.
#370000000000
0!
0.
#375000000000
1!
1.
#380000000000
0!
0.
#385000000000
1!
1.
#390000000000
0!
0.
#395000000000
1!
1.
#400000000000
0!
1$
0.
10
#405000000000
1!
b0001 ,
1.
b0001 8
1:
1;
1<
b0001 J
1P
1a
1r
b0001 u
b1 w
b0001 x
b0001 y
b1 !"
#410000000000
0!
0.
0:
0;
0<
0P
0a
0r
#415000000000
1!
b0010 ,
1.
b0010 8
1:
1;
1<
b0010 J
1P
1a
1r
b0010 u
b10 w
b0010 x
b0010 y
b10 !"
#420000000000
0!
0.
0:
0;
0<
0P
0a
0r
#425000000000
1!
b0011 ,
1.
b0011 8
1:
1;
1<
b0011 J
1P
1a
1r
b0011 u
b11 w
b0011 x
b0011 y
b11 !"
#430000000000
0!
0.
0:
0;
0<
0P
0a
0r
#435000000000
1!
b0100 ,
1.
b0100 8
1:
1;
1<
b0100 J
1P
1a
1r
b0100 u
b100 w
b0100 x
b0100 y
b100 !"
#440000000000
0!
0.
0:
0;
0<
0P
0a
0r
#445000000000
1!
b0101 ,
1.
b0101 8
1:
1;
1<
b0101 J
1P
1a
1r
b0101 u
b101 w
b0101 x
b0101 y
b101 !"
#450000000000
0!
0.
0:
0;
0<
0P
0a
0r
#455000000000
1!
b0110 ,
1.
b0110 8
1:
1;
1<
b0110 J
1P
1a
1r
b0110 u
b110 w
b0110 x
b0110 y
b110 !"
#460000000000
0!
0.
0:
0;
0<
0P
0a
0r
#465000000000
1!
b0111 ,
1.
b0111 8
1:
1;
1<
b0111 J
1P
1a
1r
b0111 u
b111 w
b0111 x
b0111 y
b111 !"
#470000000000
0!
0.
0:
0;
0<
0P
0a
0r
#475000000000
1!
b1000 ,
1.
b1000 8
1:
1;
1<
b1000 J
1P
1a
1r
b1000 u
b1000 w
b1000 x
b1000 y
b1000 !"
#480000000000
0!
0.
0:
0;
0<
0P
0a
0r
#485000000000
1!
b1001 ,
1.
b1001 8
1:
1;
1<
b1001 J
1P
1a
1r
b1001 u
b1001 w
b1001 x
b1001 y
b1001 !"
1#"
0%"
#485005000000
b0001 -
b0001 9
1=
0B
1F
b0001 K
0v
1{
0}
1&"
b0001 )"
b1 +"
b0001 ,"
b0001 -"
b1 2"
#490000000000
0!
0.
0:
0;
0<
0=
0P
0a
0r
0&"
#495000000000
1!
b0000 ,
b0010 -
1.
b0000 8
b0010 9
1:
1;
1<
1=
b0000 J
b0010 K
1P
1a
1r
b0000 u
b0 w
b0000 x
b0000 y
b0 !"
0#"
1%"
1&"
b0010 )"
b10 +"
b0010 ,"
b0010 -"
b10 2"
#495005000000
0=
1B
0F
1v
0{
1}
0&"
#500000000000
0!
0.
0:
0;
0<
0P
0a
0r
#505000000000
1!
b0001 ,
1.
b0001 8
1:
1;
1<
b0001 J
1P
1a
1r
b0001 u
b1 w
b0001 x
b0001 y
b1 !"
#510000000000
0!
0.
0:
0;
0<
0P
0a
0r
#515000000000
1!
b0010 ,
1.
b0010 8
1:
1;
1<
b0010 J
1P
1a
1r
b0010 u
b10 w
b0010 x
b0010 y
b10 !"
#520000000000
0!
0.
0:
0;
0<
0P
0a
0r
#525000000000
1!
b0011 ,
1.
b0011 8
1:
1;
1<
b0011 J
1P
1a
1r
b0011 u
b11 w
b0011 x
b0011 y
b11 !"
#530000000000
0!
0.
0:
0;
0<
0P
0a
0r
#535000000000
1!
b0100 ,
1.
b0100 8
1:
1;
1<
b0100 J
1P
1a
1r
b0100 u
b100 w
b0100 x
b0100 y
b100 !"
#540000000000
0!
0.
0:
0;
0<
0P
0a
0r
#545000000000
1!
b0101 ,
1.
b0101 8
1:
1;
1<
b0101 J
1P
1a
1r
b0101 u
b101 w
b0101 x
b0101 y
b101 !"
#550000000000
0!
0.
0:
0;
0<
0P
0a
0r
#555000000000
1!
b0110 ,
1.
b0110 8
1:
1;
1<
b0110 J
1P
1a
1r
b0110 u
b110 w
b0110 x
b0110 y
b110 !"
#560000000000
0!
0.
0:
0;
0<
0P
0a
0r
#565000000000
1!
b0111 ,
1.
b0111 8
1:
1;
1<
b0111 J
1P
1a
1r
b0111 u
b111 w
b0111 x
b0111 y
b111 !"
#570000000000
0!
0.
0:
0;
0<
0P
0a
0r
#575000000000
1!
b1000 ,
1.
b1000 8
1:
1;
1<
b1000 J
1P
1a
1r
b1000 u
b1000 w
b1000 x
b1000 y
b1000 !"
#580000000000
0!
0.
0:
0;
0<
0P
0a
0r
#585000000000
1!
b1001 ,
1.
b1001 8
1:
1;
1<
b1001 J
1P
1a
1r
b1001 u
b1001 w
b1001 x
b1001 y
b1001 !"
1#"
0%"
#585005000000
b0011 -
b0011 9
1=
0B
1F
b0011 K
0v
1{
0}
1&"
b0011 )"
b11 +"
b0011 ,"
b0011 -"
b11 2"
#590000000000
0!
0.
0:
0;
0<
0=
0P
0a
0r
0&"
#595000000000
1!
b0000 ,
b0100 -
1.
b0000 8
b0100 9
1:
1;
1<
1=
b0000 J
b0100 K
1P
1a
1r
b0000 u
b0 w
b0000 x
b0000 y
b0 !"
0#"
1%"
1&"
b0100 )"
b100 +"
b0100 ,"
b0100 -"
b100 2"
#595005000000
0=
1B
0F
1v
0{
1}
0&"
#600000000000
0!
0.
0:
0;
0<
0P
0a
0r
#605000000000
1!
b0001 ,
1.
b0001 8
1:
1;
1<
b0001 J
1P
1a
1r
b0001 u
b1 w
b0001 x
b0001 y
b1 !"
#610000000000
0!
0.
0:
0;
0<
0P
0a
0r
#615000000000
1!
b0010 ,
1.
b0010 8
1:
1;
1<
b0010 J
1P
1a
1r
b0010 u
b10 w
b0010 x
b0010 y
b10 !"
#620000000000
0!
0.
0:
0;
0<
0P
0a
0r
#625000000000
1!
b0011 ,
1.
b0011 8
1:
1;
1<
b0011 J
1P
1a
1r
b0011 u
b11 w
b0011 x
b0011 y
b11 !"
#630000000000
0!
0.
0:
0;
0<
0P
0a
0r
#635000000000
1!
b0100 ,
1.
b0100 8
1:
1;
1<
b0100 J
1P
1a
1r
b0100 u
b100 w
b0100 x
b0100 y
b100 !"
#640000000000
0!
0.
0:
0;
0<
0P
0a
0r
#645000000000
1!
b0101 ,
1.
b0101 8
1:
1;
1<
b0101 J
1P
1a
1r
b0101 u
b101 w
b0101 x
b0101 y
b101 !"
#650000000000
0!
0.
0:
0;
0<
0P
0a
0r
#655000000000
1!
b0110 ,
1.
b0110 8
1:
1;
1<
b0110 J
1P
1a
1r
b0110 u
b110 w
b0110 x
b0110 y
b110 !"
#660000000000
0!
0.
0:
0;
0<
0P
0a
0r
#665000000000
1!
b0111 ,
1.
b0111 8
1:
1;
1<
b0111 J
1P
1a
1r
b0111 u
b111 w
b0111 x
b0111 y
b111 !"
#670000000000
0!
0.
0:
0;
0<
0P
0a
0r
#675000000000
1!
b1000 ,
1.
b1000 8
1:
1;
1<
b1000 J
1P
1a
1r
b1000 u
b1000 w
b1000 x
b1000 y
b1000 !"
#680000000000
0!
0.
0:
0;
0<
0P
0a
0r
#685000000000
1!
b1001 ,
1.
b1001 8
1:
1;
1<
b1001 J
1P
1a
1r
b1001 u
b1001 w
b1001 x
b1001 y
b1001 !"
1#"
0%"
#685005000000
b0101 -
b0101 9
1=
0B
1F
b0101 K
0v
1{
0}
1&"
b0101 )"
b101 +"
b0101 ,"
b0101 -"
b101 2"
#690000000000
0!
0.
0:
0;
0<
0=
0P
0a
0r
0&"
#695000000000
1!
b0000 ,
b0110 -
1.
b0000 8
b0110 9
1:
1;
1<
1=
b0000 J
b0110 K
1P
1a
1r
b0000 u
b0 w
b0000 x
b0000 y
b0 !"
0#"
1%"
1&"
b0110 )"
b110 +"
b0110 ,"
b0110 -"
b110 2"
#695005000000
0=
1B
0F
1v
0{
1}
0&"
#700000000000
0!
0.
0:
0;
0<
0P
0a
0r
#705000000000
1!
b0001 ,
1.
b0001 8
1:
1;
1<
b0001 J
1P
1a
1r
b0001 u
b1 w
b0001 x
b0001 y
b1 !"
#710000000000
0!
0.
0:
0;
0<
0P
0a
0r
#715000000000
1!
b0010 ,
1.
b0010 8
1:
1;
1<
b0010 J
1P
1a
1r
b0010 u
b10 w
b0010 x
b0010 y
b10 !"
#720000000000
0!
0.
0:
0;
0<
0P
0a
0r
#725000000000
1!
b0011 ,
1.
b0011 8
1:
1;
1<
b0011 J
1P
1a
1r
b0011 u
b11 w
b0011 x
b0011 y
b11 !"
#730000000000
0!
0.
0:
0;
0<
0P
0a
0r
#735000000000
1!
b0100 ,
1.
b0100 8
1:
1;
1<
b0100 J
1P
1a
1r
b0100 u
b100 w
b0100 x
b0100 y
b100 !"
#740000000000
0!
0.
0:
0;
0<
0P
0a
0r
#745000000000
1!
b0101 ,
1.
b0101 8
1:
1;
1<
b0101 J
1P
1a
1r
b0101 u
b101 w
b0101 x
b0101 y
b101 !"
#750000000000
0!
0.
0:
0;
0<
0P
0a
0r
#755000000000
1!
b0110 ,
1.
b0110 8
1:
1;
1<
b0110 J
1P
1a
1r
b0110 u
b110 w
b0110 x
b0110 y
b110 !"
#760000000000
0!
0.
0:
0;
0<
0P
0a
0r
#765000000000
1!
b0111 ,
1.
b0111 8
1:
1;
1<
b0111 J
1P
1a
1r
b0111 u
b111 w
b0111 x
b0111 y
b111 !"
#770000000000
0!
0.
0:
0;
0<
0P
0a
0r
#775000000000
1!
b1000 ,
1.
b1000 8
1:
1;
1<
b1000 J
1P
1a
1r
b1000 u
b1000 w
b1000 x
b1000 y
b1000 !"
#780000000000
0!
0.
0:
0;
0<
0P
0a
0r
#785000000000
1!
b1001 ,
1.
b1001 8
1:
1;
1<
b1001 J
1P
1a
1r
b1001 u
b1001 w
b1001 x
b1001 y
b1001 !"
1#"
0%"
#785005000000
b0111 -
b0111 9
1=
0B
1F
b0111 K
0v
1{
0}
1&"
b0111 )"
b111 +"
b0111 ,"
b0111 -"
b111 2"
#790000000000
0!
0.
0:
0;
0<
0=
0P
0a
0r
0&"
#795000000000
1!
b0000 ,
b1000 -
1.
b0000 8
b1000 9
1:
1;
1<
1=
b0000 J
b1000 K
1P
1a
1r
b0000 u
b0 w
b0000 x
b0000 y
b0 !"
0#"
1%"
1&"
b1000 )"
b1000 +"
b1000 ,"
b1000 -"
b1000 2"
#795005000000
0=
1B
0F
1v
0{
1}
0&"
#800000000000
0!
0.
0:
0;
0<
0P
0a
0r
#805000000000
1!
b0001 ,
1.
b0001 8
1:
1;
1<
b0001 J
1P
1a
1r
b0001 u
b1 w
b0001 x
b0001 y
b1 !"
#810000000000
0!
0.
0:
0;
0<
0P
0a
0r
#815000000000
1!
b0010 ,
1.
b0010 8
1:
1;
1<
b0010 J
1P
1a
1r
b0010 u
b10 w
b0010 x
b0010 y
b10 !"
#820000000000
0!
0.
0:
0;
0<
0P
0a
0r
#825000000000
1!
b0011 ,
1.
b0011 8
1:
1;
1<
b0011 J
1P
1a
1r
b0011 u
b11 w
b0011 x
b0011 y
b11 !"
#830000000000
0!
0.
0:
0;
0<
0P
0a
0r
#835000000000
1!
b0100 ,
1.
b0100 8
1:
1;
1<
b0100 J
1P
1a
1r
b0100 u
b100 w
b0100 x
b0100 y
b100 !"
#840000000000
0!
0.
0:
0;
0<
0P
0a
0r
#845000000000
1!
b0101 ,
1.
b0101 8
1:
1;
1<
b0101 J
1P
1a
1r
b0101 u
b101 w
b0101 x
b0101 y
b101 !"
#850000000000
0!
0.
0:
0;
0<
0P
0a
0r
#855000000000
1!
b0110 ,
1.
b0110 8
1:
1;
1<
b0110 J
1P
1a
1r
b0110 u
b110 w
b0110 x
b0110 y
b110 !"
#860000000000
0!
0.
0:
0;
0<
0P
0a
0r
#865000000000
1!
b0111 ,
1.
b0111 8
1:
1;
1<
b0111 J
1P
1a
1r
b0111 u
b111 w
b0111 x
b0111 y
b111 !"
#870000000000
0!
0.
0:
0;
0<
0P
0a
0r
#875000000000
1!
b1000 ,
1.
b1000 8
1:
1;
1<
b1000 J
1P
1a
1r
b1000 u
b1000 w
b1000 x
b1000 y
b1000 !"
#880000000000
0!
0.
0:
0;
0<
0P
0a
0r
#885000000000
1!
b1001 ,
1.
b1001 8
1:
1;
1<
b1001 J
1P
1a
1r
b1001 u
b1001 w
b1001 x
b1001 y
b1001 !"
1#"
0%"
#885005000000
b1001 -
b1001 9
1=
0B
1F
b1001 K
0v
1{
0}
1&"
b1001 )"
b1001 +"
b1001 ,"
b1001 -"
b1001 2"
14"
06"
#885010000000
0C
1G
0*"
1/"
01"
#890000000000
0!
0.
0:
0;
0<
0=
0P
0a
0r
0&"
#895000000000
1!
b0000 ,
b0000 -
1.
b0000 8
b0000 9
1:
1;
1<
1=
b0000 J
b0000 K
1P
1a
1r
b0000 u
b0 w
b0000 x
b0000 y
b0 !"
0#"
1%"
1&"
b0000 )"
b0 +"
b0000 ,"
b0000 -"
b0 2"
04"
16"
#895005000000
0=
1B
1C
0F
0G
1v
0{
1}
0&"
1*"
0/"
11"
#900000000000
0!
0.
0:
0;
0<
0P
0a
0r
#905000000000
1!
b0001 ,
1.
b0001 8
1:
1;
1<
b0001 J
1P
1a
1r
b0001 u
b1 w
b0001 x
b0001 y
b1 !"
#910000000000
0!
0.
0:
0;
0<
0P
0a
0r
#915000000000
1!
b0010 ,
1.
b0010 8
1:
1;
1<
b0010 J
1P
1a
1r
b0010 u
b10 w
b0010 x
b0010 y
b10 !"
#920000000000
0!
0.
0:
0;
0<
0P
0a
0r
#925000000000
1!
b0011 ,
1.
b0011 8
1:
1;
1<
b0011 J
1P
1a
1r
b0011 u
b11 w
b0011 x
b0011 y
b11 !"
#930000000000
0!
0.
0:
0;
0<
0P
0a
0r
#935000000000
1!
b0100 ,
1.
b0100 8
1:
1;
1<
b0100 J
1P
1a
1r
b0100 u
b100 w
b0100 x
b0100 y
b100 !"
#940000000000
0!
0.
0:
0;
0<
0P
0a
0r
#945000000000
1!
b0101 ,
1.
b0101 8
1:
1;
1<
b0101 J
1P
1a
1r
b0101 u
b101 w
b0101 x
b0101 y
b101 !"
#950000000000
0!
0.
0:
0;
0<
0P
0a
0r
#955000000000
1!
b0110 ,
1.
b0110 8
1:
1;
1<
b0110 J
1P
1a
1r
b0110 u
b110 w
b0110 x
b0110 y
b110 !"
#960000000000
0!
0.
0:
0;
0<
0P
0a
0r
#965000000000
1!
b0111 ,
1.
b0111 8
1:
1;
1<
b0111 J
1P
1a
1r
b0111 u
b111 w
b0111 x
b0111 y
b111 !"
#970000000000
0!
0.
0:
0;
0<
0P
0a
0r
#975000000000
1!
b1000 ,
1.
b1000 8
1:
1;
1<
b1000 J
1P
1a
1r
b1000 u
b1000 w
b1000 x
b1000 y
b1000 !"
#980000000000
0!
0.
0:
0;
0<
0P
0a
0r
#985000000000
1!
b1001 ,
1.
b1001 8
1:
1;
1<
b1001 J
1P
1a
1r
b1001 u
b1001 w
b1001 x
b1001 y
b1001 !"
1#"
0%"
#985005000000
b0001 -
b0001 9
1=
0B
1F
b0001 K
0v
1{
0}
1&"
b0001 )"
b1 +"
b0001 ,"
b0001 -"
b1 2"
#990000000000
0!
0.
0:
0;
0<
0=
0P
0a
0r
0&"
